baher_hasab/__init__.py
baher_hasab/baher_hasab.py
baher_hasab/helper.py
baher_hasab/lookups.py
baher_hasab-1.1.1.dist-info/LICENSE
baher_hasab-1.1.1.dist-info/METADATA
baher_hasab-1.1.1.dist-info/WHEEL
baher_hasab-1.1.1.dist-info/top_level.txt
baher_hasab-1.1.1.dist-info/RECORD
