Metadata-Version: 2.2
Name: baher_hasab
Version: 1.1.1
Summary: A python package for calculating Ethiopian holidays and fasting seasons
Home-page: https://sam23121.github.io/baher_hasab
Author: Samuel Alene
Author-email: Samuel Alene <smlalene@gmail.com>
License: MIT License
Project-URL: Homepage, https://github.com/sam23121/baher_hasab
Project-URL: Docs, https://sam23121.github.io/baher_hasab/
Keywords: baher_hasab,abushar,ethiopia
Classifier: License :: OSI Approved :: MIT License
Classifier: Programming Language :: Python
Classifier: Programming Language :: Python :: 3
Requires-Python: >=3.7
License-File: LICENSE
